gemini_torch/__init__.py
gemini_torch/long_gemini.py
gemini_torch/model.py
gemini_torch/omni_modality_processor.py
gemini_torch/tokenizer.py
gemini_torch/transformer.py
gemini_torch-0.2.5.dist-info/LICENSE
gemini_torch-0.2.5.dist-info/WHEEL
gemini_torch-0.2.5.dist-info/METADATA
gemini_torch-0.2.5.dist-info/RECORD
